LICENSE
README.md
pyproject.toml
st_zig/ZigCompiler.py
st_zig/__init__.py
st_zig/build_meta.py
st_zig/enforce.py
st_zig.egg-info/PKG-INFO
st_zig.egg-info/SOURCES.txt
st_zig.egg-info/dependency_links.txt
st_zig.egg-info/requires.txt
st_zig.egg-info/top_level.txt
tests/test_project.py