Metadata-Version: 2.4
Name: st_zig
Version: 0.1.1
Summary: A setuptools extension for compiling native extensions with Zig.
Author-email: Rudolf Kolbe <rkolbe96@gmail.com>
License-Expression: MIT
Project-URL: Homepage, https://github.com/K0lb3/st_zig
Project-URL: Bug Tracker, https://github.com/K0lb3/st_zig/issues
Requires-Python: >=3.7
License-File: LICENSE
Requires-Dist: setuptools
Requires-Dist: ziglang
Dynamic: license-file
